[
  {
    "_id": "000000000000000000000467",
    "name": "Сахарная пудра",
    "category": [
      "sweet"
    ],
    "description": "Для украшения и выпечки"
  },
  {
    "_id": "000000000000000000000468",
    "name": "Какао-порошок",
    "category": [
      "sweet"
    ],
    "description": "Для шоколадных десертов"
  },
  {
    "_id": "000000000000000000000469",
    "name": "Шоколад черный",
    "category": [
      "sweet"
    ],
    "description": "Для приготовления десертов"
  },
  {
    "_id": "000000000000000000000470",
    "name": "Шоколад молочный",
    "category": [
      "sweet"
    ],
    "description": "Для десертов и напитков"
  },
  {
    "_id": "000000000000000000000471",
    "name": "Шоколад белый",
    "category": [
      "sweet"
    ],
    "description": "Для конфет и глазури"
  },
  {
    "_id": "000000000000000000000472",
    "name": "Мармелад",
    "category": [
      "sweet"
    ],
    "description": "Для украшения и начинки"
  },
  {
    "_id": "000000000000000000000473",
    "name": "Мед",
    "category": [
      "sweet"
    ],
    "description": "Для выпечки и соусов"
  },
  {
    "_id": "000000000000000000000474",
    "name": "Сгущенное молоко",
    "category": [
      "sweet"
    ],
    "description": "Для десертов и кремов"
  },
  {
    "_id": "000000000000000000000475",
    "name": "Ванильный сахар",
    "category": [
      "sweet"
    ],
    "description": "Для аромата в выпечке"
  },
  {
    "_id": "000000000000000000000477",
    "name": "Карамель",
    "category": [
      "sweet"
    ],
    "description": "Для украшения и начинки"
  },
  {
    "_id": "000000000000000000000478",
    "name": "Кокосовая стружка",
    "category": [
      "sweet"
    ],
    "description": "Для украшения и выпечки"
  },
  {
    "_id": "000000000000000000000479",
    "name": "Ореховая паста",
    "category": [
      "sweet"
    ],
    "description": "Для начинки и десертов"
  },
  {
    "_id": "000000000000000000000480",
    "name": "Сироп кленовый",
    "category": [
      "sweet"
    ],
    " description": "Для блинчиков и десертов"
  },
  {
    "_id": "000000000000000000000481",
    "name": "Сироп шоколадный",
    "category": [
      "sweet"
    ],
    "description": "Для мороженого и напитков"
  },
  {
    "_id": "000000000000000000000482",
    "name": "Сироп карамельный",
    "category": [
      "sweet"
    ],
    "description": "Для десертов и кофе"
  },
  {
    "_id": "000000000000000000000483",
    "name": "Печенье крошка",
    "category": [
      "sweet"
    ],
    "description": "Для приготовления десертов"
  },
  {
    "_id": "000000000000000000000484",
    "name": "Сухофрукты",
    "category": [
      "sweet"
    ],
    "description": "Для выпечки и десертов"
  },
  {
    "_id": "000000000000000000000485",
    "name": "Финики",
    "category": [
      "sweet"
    ],
    "description": "Для сладких блюд и закусок"
  },
  {
    "_id": "000000000000000000000486",
    "name": "Курага",
    "category": [
      "sweet"
    ],
    "description": "Для выпечки и десертов"
  },
  {
    "_id": "000000000000000000000487",
    "name": "Изюм",
    "category": [
      "sweet"
    ],
    "description": "Для выпечки и закусок"
  },
  {
    "_id": "000000000000000000000488",
    "name": "Цукаты",
    "category": [
      "sweet"
    ],
    "description": "Для украшения и выпечки"
  },
  {
    "_id": "000000000000000000000489",
    "name": "Патока",
    "category": [
      "sweet"
    ],
    "description": "Для приготовления десертов"
  },
  {
    "_id": "000000000000000000000490",
    "name": "Карамельные капли",
    "category": [
      "sweet"
    ],
    "description": "Для украшения и добавления в блюда"
  },
  {
    "_id": "000000000000000000000491",
    "name": "Цитрусовая цедра",
    "category": [
      "sweet"
    ],
    "description": "Для аромата в десертах"
  }
]